{
  "generated_at": "2025-10-21T05:04:00Z",
  "count": 80,
  "items": [
    {
      "section": "publications",
      "page": 1,
      "title": "The status of women in agrifood systems in sub-Saharan Africa - Overview",
      "date": "02/09/2025",
      "date_iso": "2025-09-02",
      "year": 2025,
      "month": 9,
      "category": "Gender and inclusive food systems and value chains",
      "url": "https://openknowledge.fao.org/handle/20.500.14283/cd6631en",
      "summary": "",
      "article_summary": "",
      "article_text": ""
    },
    {
      "section": "publications",
      "page": 1,
      "title": "Europe and Central Asia Gender Newsletter, August 2025 – Issue #19",
      "date": "01/09/2025",
      "date_iso": "2025-09-01",
      "year": 2025,
      "month": 9,
      "category": "Gender equality and women's empowerment",
      "url": "https://openknowledge.fao.org/handle/20.500.14283/cd6759en",
      "summary": "",
      "article_summary": "",
      "article_text": ""
    },
    {
      "section": "publications",
      "page": 1,
      "title": "Gender equality and climate change: A synthesis of knowledge in agrifood systems",
      "date": "01/09/2025",
      "date_iso": "2025-09-01",
      "year": 2025,
      "month": 9,
      "category": "Gender and climate change, agroecology and biodiversity",
      "url": "https://openknowledge.fao.org/handle/20.500.14283/cd4349en",
      "summary": "",
      "article_summary": "",
      "article_text": ""
    },
    {
      "section": "publications",
      "page": 1,
      "title": "Republic of Tajikistan: National gender profile of agriculture and rural livelihoods (Country Gender Assessment Series)",
      "date": "01/08/2025",
      "date_iso": "2025-08-01",
      "year": 2025,
      "month": 8,
      "category": "Gender analysis, gender mainstreaming and the project cycle",
      "url": "https://openknowledge.fao.org/handle/20.500.14283/cd6263en",
      "summary": "",
      "article_summary": "",
      "article_text": ""
    },
    {
      "section": "publications",
      "page": 1,
      "title": "Understanding women’s roles and trade potential along regional value chains: An in-depth analysis of the soybean-to-poultry value chain in the United Republic of Tanzania",
      "date": "01/08/2025",
      "date_iso": "2025-08-01",
      "year": 2025,
      "month": 8,
      "category": "Gender and inclusive food systems and value chains",
      "url": "https://openknowledge.fao.org/handle/20.500.14283/cd5068en",
      "summary": "",
      "article_summary": "",
      "article_text": ""
    },
    {
      "section": "publications",
      "page": 1,
      "title": "The empowerment of rural women, gender-responsive land policies and the implementation of Sustainable Development Goal Indicators 5.a.1 and 5.a.2. Assessment report 2025",
      "date": "01/08/2025",
      "date_iso": "2025-08-01",
      "year": 2025,
      "month": 8,
      "category": "Gender equality and women's empowerment",
      "url": "https://openknowledge.fao.org/handle/20.500.14283/cd5891en",
      "summary": "",
      "article_summary": "",
      "article_text": ""
    },
    {
      "section": "publications",
      "page": 1,
      "title": "Gender dynamics in pesticide use and management in Central Asia and Türkiye (Policy paper)",
      "date": "01/07/2025",
      "date_iso": "2025-07-01",
      "year": 2025,
      "month": 7,
      "category": "Gender and plant production and protection",
      "url": "https://openknowledge.fao.org/handle/20.500.14283/cd5800en",
      "summary": "",
      "article_summary": "",
      "article_text": ""
    },
    {
      "section": "publications",
      "page": 1,
      "title": "Joint Programme on Gender Transformative Approaches for Food Security and Nutrition: 2019-2024",
      "date": "01/07/2025",
      "date_iso": "2025-07-01",
      "year": 2025,
      "month": 7,
      "category": "Gender and food security and nutrition",
      "url": "https://openknowledge.fao.org/handle/20.500.14283/cd5994en",
      "summary": "",
      "article_summary": "",
      "article_text": ""
    },
    {
      "section": "publications",
      "page": 2,
      "title": "Promoting the dissemination and uptake of the​ Voluntary Guidelines on Gender Equality and Women’s and Girls’ Empowerment in the Context of Food Security and Nutrition (Programme overview 2025-2027)",
      "date": "01/07/2025",
      "date_iso": "2025-07-01",
      "year": 2025,
      "month": 7,
      "category": "Gender equality and women's empowerment",
      "url": "https://openknowledge.fao.org/handle/20.500.14283/cd6061en",
      "summary": "",
      "article_summary": "",
      "article_text": ""
    },
    {
      "section": "publications",
      "page": 2,
      "title": "Joint Programme on Gender Transformative Approaches for Food Security and Nutrition: 2019-2024",
      "date": "01/07/2025",
      "date_iso": "2025-07-01",
      "year": 2025,
      "month": 7,
      "category": "Gender and food security and nutrition",
      "url": "https://openknowledge.fao.org/handle/20.500.14283/cd5994en",
      "summary": "",
      "article_summary": "",
      "article_text": ""
    },
    {
      "section": "publications",
      "page": 2,
      "title": "Child Labour Global Estimates 2024",
      "date": "11/06/2025",
      "date_iso": "2025-06-11",
      "year": 2025,
      "month": 6,
      "category": "Gender and decent rural employment and child labour",
      "url": "https://data.unicef.org/resources/child-labour-global-estimates-2024/",
      "summary": "",
      "article_summary": "",
      "article_text": ""
    },
    {
      "section": "publications",
      "page": 2,
      "title": "Africa Gender Newsletter, June 2025 – Issue #1",
      "date": "01/06/2025",
      "date_iso": "2025-06-01",
      "year": 2025,
      "month": 6,
      "category": "Gender equality and women's empowerment",
      "url": "https://openknowledge.fao.org/handle/20.500.14283/cd5748en",
      "summary": "",
      "article_summary": "",
      "article_text": ""
    },
    {
      "section": "publications",
      "page": 2,
      "title": "Bringing women innovators to the fore: Engaging in gender-responsive, farmer-led innovation and research (Guidelines for facilitators)",
      "date": "01/06/2025",
      "date_iso": "2025-06-01",
      "year": 2025,
      "month": 6,
      "category": "Gender and innovative and labour-saving technologies",
      "url": "https://openknowledge.fao.org/handle/20.500.14283/cd0954en",
      "summary": "",
      "article_summary": "",
      "article_text": ""
    },
    {
      "section": "publications",
      "page": 2,
      "title": "Walking the talk: Advancing parliamentary action for gender equality and investments in the agrifood sector",
      "date": "01/06/2025",
      "date_iso": "2025-06-01",
      "year": 2025,
      "month": 6,
      "category": "Gender and investment in sustainable agrifood systems",
      "url": "https://openknowledge.fao.org/handle/20.500.14283/cd1687en",
      "summary": "",
      "article_summary": "",
      "article_text": ""
    },
    {
      "section": "publications",
      "page": 2,
      "title": "Scoping paper on complementary social protection and economic inclusion programming for rural women’s economic empowerment",
      "date": "01/06/2025",
      "date_iso": "2025-06-01",
      "year": 2025,
      "month": 6,
      "category": "Gender equality and women's empowerment",
      "url": "https://openknowledge.fao.org/handle/20.500.14283/cd6012en",
      "summary": "",
      "article_summary": "",
      "article_text": ""
    },
    {
      "section": "publications",
      "page": 2,
      "title": "Gender Asia Pacific Newsletter, May 2025 – Issue #6",
      "date": "01/05/2025",
      "date_iso": "2025-05-01",
      "year": 2025,
      "month": 5,
      "category": "Gender equality and women's empowerment",
      "url": "https://openknowledge.fao.org/handle/20.500.14283/cd5510en",
      "summary": "",
      "article_summary": "",
      "article_text": ""
    },
    {
      "section": "publications",
      "page": 3,
      "title": "Gender-responsive budgeting to realize women’s and girls’ right to adequate food",
      "date": "01/05/2025",
      "date_iso": "2025-05-01",
      "year": 2025,
      "month": 5,
      "category": "Gender-responsive policy making and budgeting",
      "url": "https://openknowledge.fao.org/handle/20.500.14283/cd5220en",
      "summary": "",
      "article_summary": "",
      "article_text": ""
    },
    {
      "section": "publications",
      "page": 3,
      "title": "Republic of Belarus: National gender profile of agriculture and rural livelihoods (Country Gender Assessment Series)",
      "date": "01/05/2025",
      "date_iso": "2025-05-01",
      "year": 2025,
      "month": 5,
      "category": "Gender analysis, gender mainstreaming and the project cycle",
      "url": "https://openknowledge.fao.org/handle/20.500.14283/cd5325en",
      "summary": "",
      "article_summary": "",
      "article_text": ""
    },
    {
      "section": "publications",
      "page": 3,
      "title": "Development finance for gender equality and women’s empowerment in agrifood systems",
      "date": "01/04/2025",
      "date_iso": "2025-04-01",
      "year": 2025,
      "month": 4,
      "category": "Gender equality and women's empowerment",
      "url": "https://openknowledge.fao.org/handle/20.500.14283/cd5017en",
      "summary": "",
      "article_summary": "",
      "article_text": ""
    },
    {
      "section": "publications",
      "page": 3,
      "title": "Gender-inclusive toolkit for financial institutions in sub-Saharan Africa: Making the African Continental Free Trade Area work for women",
      "date": "26/03/2025",
      "date_iso": "2025-03-26",
      "year": 2025,
      "month": 3,
      "category": "Gender and inclusive food systems and value chains",
      "url": "https://openknowledge.fao.org/handle/20.500.14283/cd3741en",
      "summary": "",
      "article_summary": "",
      "article_text": ""
    },
    {
      "section": "publications",
      "page": 3,
      "title": "Commit to Grow Equality: Investing in the future of women in agrifood systems - Progress report 2025",
      "date": "12/03/2025",
      "date_iso": "2025-03-12",
      "year": 2025,
      "month": 3,
      "category": "Gender and inclusive food systems and value chains",
      "url": "https://openknowledge.fao.org/handle/20.500.14283/cd4123en",
      "summary": "",
      "article_summary": "",
      "article_text": ""
    },
    {
      "section": "publications",
      "page": 3,
      "title": "Europe and Central Asia Gender Newsletter, March 2025 – Issue #17",
      "date": "01/03/2025",
      "date_iso": "2025-03-01",
      "year": 2025,
      "month": 3,
      "category": "Gender equality and women's empowerment",
      "url": "https://openknowledge.fao.org/handle/20.500.14283/cd4667en",
      "summary": "",
      "article_summary": "",
      "article_text": ""
    },
    {
      "section": "publications",
      "page": 3,
      "title": "Empowering women veterinary paraprofessionals through gender-responsive training",
      "date": "01/02/2025",
      "date_iso": "2025-02-01",
      "year": 2025,
      "month": 2,
      "category": "Gender equality and women's empowerment",
      "url": "https://openknowledge.fao.org/handle/20.500.14283/cd4109en",
      "summary": "",
      "article_summary": "",
      "article_text": ""
    },
    {
      "section": "publications",
      "page": 3,
      "title": "Mainstreaming gender in national drought plans, national action plans and national policies",
      "date": "01/02/2025",
      "date_iso": "2025-02-01",
      "year": 2025,
      "month": 2,
      "category": "Gender analysis, gender mainstreaming and the project cycle",
      "url": "https://openknowledge.fao.org/handle/20.500.14283/cd4147en",
      "summary": "",
      "article_summary": "",
      "article_text": ""
    },
    {
      "section": "publications",
      "page": 4,
      "title": "Rural transformation through agribusiness incubation",
      "date": "01/02/2025",
      "date_iso": "2025-02-01",
      "year": 2025,
      "month": 2,
      "category": "Gender equality and women's empowerment",
      "url": "https://openknowledge.fao.org/handle/20.500.14283/cd3971en",
      "summary": "",
      "article_summary": "",
      "article_text": ""
    },
    {
      "section": "publications",
      "page": 4,
      "title": "A gender-responsive methodology for fish loss assessment in the small-scale fisheries sector",
      "date": "01/02/2025",
      "date_iso": "2025-02-01",
      "year": 2025,
      "month": 2,
      "category": "Gender in fisheries and aquaculture",
      "url": "https://openknowledge.fao.org/handle/20.500.14283/cd4304en",
      "summary": "",
      "article_summary": "",
      "article_text": ""
    },
    {
      "section": "publications",
      "page": 4,
      "title": "Gender transformative change for climate action",
      "date": "01/01/2025",
      "date_iso": "2025-01-01",
      "year": 2025,
      "month": 1,
      "category": "Gender and climate change, agroecology and biodiversity",
      "url": "https://openknowledge.fao.org/handle/20.500.14283/cd3900en",
      "summary": "",
      "article_summary": "",
      "article_text": ""
    },
    {
      "section": "publications",
      "page": 4,
      "title": "Georgia: National gender profile of agriculture and rural livelihoods (Country Gender Assessment Series)",
      "date": "01/01/2025",
      "date_iso": "2025-01-01",
      "year": 2025,
      "month": 1,
      "category": "Gender analysis, gender mainstreaming and the project cycle",
      "url": "https://openknowledge.fao.org/handle/20.500.14283/cd3777en",
      "summary": "",
      "article_summary": "",
      "article_text": ""
    },
    {
      "section": "publications",
      "page": 4,
      "title": "Step-by-step guide to integrating a gender transformative approach throughout the project cycle",
      "date": "01/12/2024",
      "date_iso": "2024-12-01",
      "year": 2024,
      "month": 12,
      "category": "Gender analysis, gender mainstreaming and the project cycle",
      "url": "https://openknowledge.fao.org/handle/20.500.14283/cd2629en",
      "summary": "",
      "article_summary": "",
      "article_text": ""
    },
    {
      "section": "publications",
      "page": 4,
      "title": "Brochure on the CFS voluntary guidelines on gender equality and women's and girls' empowerment in the context of food security and nutrition",
      "date": "12/11/2024",
      "date_iso": "2024-11-12",
      "year": 2024,
      "month": 11,
      "category": "Gender equality and women's empowerment",
      "url": "https://openknowledge.fao.org/handle/20.500.14283/cd3022en",
      "summary": "",
      "article_summary": "",
      "article_text": ""
    },
    {
      "section": "publications",
      "page": 4,
      "title": "CFS voluntary guidelines on gender equality and women's and girls' empowerment in the context of food security and nutrition",
      "date": "12/11/2024",
      "date_iso": "2024-11-12",
      "year": 2024,
      "month": 11,
      "category": "Gender equality and women's empowerment",
      "url": "https://openknowledge.fao.org/handle/20.500.14283/cd2996en",
      "summary": "",
      "article_summary": "",
      "article_text": ""
    },
    {
      "section": "publications",
      "page": 4,
      "title": "Report of the World Banana Forum's webinar on \"Closing the gender pay gap by increasing women's participation in banana production and leadership roles",
      "date": "06/11/2024",
      "date_iso": "2024-11-06",
      "year": 2024,
      "month": 11,
      "category": "Gender equality and women's empowerment",
      "url": "https://openknowledge.fao.org/handle/20.500.14283/cc9704en",
      "summary": "",
      "article_summary": "",
      "article_text": ""
    },
    {
      "section": "publications",
      "page": 5,
      "title": "Gender strategy for the fisheries sector in Cabo Verde",
      "date": "01/11/2024",
      "date_iso": "2024-11-01",
      "year": 2024,
      "month": 11,
      "category": "Gender in fisheries and aquaculture",
      "url": "https://openknowledge.fao.org/handle/20.500.14283/cd2830en",
      "summary": "",
      "article_summary": "",
      "article_text": ""
    },
    {
      "section": "publications",
      "page": 5,
      "title": "Strengthening Rural Populations’ Livelihoods Resilience through the Promotion Of Nonagricultural Short Circuits in the Post COVID-19 Pandemic - TCP/BRA/3802",
      "date": "01/11/2024",
      "date_iso": "2024-11-01",
      "year": 2024,
      "month": 11,
      "category": "Gender and emergencies and resilience building",
      "url": "https://openknowledge.fao.org/handle/20.500.14283/cd3054en",
      "summary": "",
      "article_summary": "",
      "article_text": ""
    },
    {
      "section": "publications",
      "page": 5,
      "title": "Supporting Gender-Responsive Adaptation to Climate Change in Kenya - UNJP/KEN/100/UWN",
      "date": "01/11/2024",
      "date_iso": "2024-11-01",
      "year": 2024,
      "month": 11,
      "category": "Gender and climate change, agroecology and biodiversity",
      "url": "https://openknowledge.fao.org/handle/20.500.14283/cd3203en",
      "summary": "",
      "article_summary": "",
      "article_text": ""
    },
    {
      "section": "publications",
      "page": 5,
      "title": "Evaluation of the project \"Empowerment of Agricultural Women Cooperatives and Producer Associations in the Agrifood Sector of Lebanon\"",
      "date": "01/11/2024",
      "date_iso": "2024-11-01",
      "year": 2024,
      "month": 11,
      "category": "Gender equality and women's empowerment",
      "url": "https://openknowledge.fao.org/handle/20.500.14283/cd3292en",
      "summary": "",
      "article_summary": "",
      "article_text": ""
    },
    {
      "section": "publications",
      "page": 5,
      "title": "Strengthening the status of the spouse and partner in Albania’s agricultural businesses",
      "date": "01/11/2024",
      "date_iso": "2024-11-01",
      "year": 2024,
      "month": 11,
      "category": "Gender equality and women's empowerment",
      "url": "https://openknowledge.fao.org/handle/20.500.14283/cd3392en",
      "summary": "",
      "article_summary": "",
      "article_text": ""
    },
    {
      "section": "publications",
      "page": 5,
      "title": "Promoting Livelihoods Recovery and Resilience through Youth and Women-Led Resilient Value Chain Development and Entrepreneurship in Saint Vincent and the Grenadines - TCP/STV/3803",
      "date": "01/11/2024",
      "date_iso": "2024-11-01",
      "year": 2024,
      "month": 11,
      "category": "Gender and emergencies and resilience building",
      "url": "https://openknowledge.fao.org/handle/20.500.14283/cd3244en",
      "summary": "",
      "article_summary": "",
      "article_text": ""
    },
    {
      "section": "publications",
      "page": 5,
      "title": "Operationalizing a Gender-Responsive Uganda National Adaptation Plan for the Agriculture Sector (NAP-Ag) - TCP/UGA/3802",
      "date": "01/11/2024",
      "date_iso": "2024-11-01",
      "year": 2024,
      "month": 11,
      "category": "Gender and climate change, agroecology and biodiversity",
      "url": "https://openknowledge.fao.org/handle/20.500.14283/cd3248en",
      "summary": "",
      "article_summary": "",
      "article_text": ""
    },
    {
      "section": "publications",
      "page": 5,
      "title": "Gender, culture and workplace health and safety in the Marshall Islands (A social sustainability management plan - March 2024)",
      "date": "01/11/2024",
      "date_iso": "2024-11-01",
      "year": 2024,
      "month": 11,
      "category": "Gender and land and water",
      "url": "https://openknowledge.fao.org/handle/20.500.14283/cd0422en",
      "summary": "",
      "article_summary": "",
      "article_text": ""
    },
    {
      "section": "publications",
      "page": 6,
      "title": "Empowering women in the Western Balkans",
      "date": "01/11/2024",
      "date_iso": "2024-11-01",
      "year": 2024,
      "month": 11,
      "category": "Gender equality and women's empowerment",
      "url": "https://openknowledge.fao.org/handle/20.500.14283/cd3418en",
      "summary": "",
      "article_summary": "",
      "article_text": ""
    },
    {
      "section": "publications",
      "page": 6,
      "title": "Empowering Rural Communities in Central Asia through Digital Transformation in Agriculture - FMM/GLO/171/MUL",
      "date": "01/11/2024",
      "date_iso": "2024-11-01",
      "year": 2024,
      "month": 11,
      "category": "Gender and innovative and labour-saving technologies",
      "url": "https://openknowledge.fao.org/handle/20.500.14283/cd3394en",
      "summary": "",
      "article_summary": "",
      "article_text": ""
    },
    {
      "section": "publications",
      "page": 6,
      "title": "Theory of change for gender transformative programming for food security, nutrition and sustainable agriculture",
      "date": "01/10/2024",
      "date_iso": "2024-10-01",
      "year": 2024,
      "month": 10,
      "category": "Gender and food security and nutrition",
      "url": "https://openknowledge.fao.org/handle/20.500.14283/cd2465en",
      "summary": "",
      "article_summary": "",
      "article_text": ""
    },
    {
      "section": "publications",
      "page": 6,
      "title": "Empowering Women’s Livelihoods in Small-Scale Fisheries in Liberia During and After COVID-19 - GCP/LIR/031/JPN",
      "date": "01/10/2024",
      "date_iso": "2024-10-01",
      "year": 2024,
      "month": 10,
      "category": "Gender in fisheries and aquaculture",
      "url": "https://openknowledge.fao.org/handle/20.500.14283/cd2947en",
      "summary": "",
      "article_summary": "",
      "article_text": ""
    },
    {
      "section": "publications",
      "page": 6,
      "title": "Climate technologies for agrifood systems transformation - Placing food security, climate change and poverty reduction at the forefront",
      "date": "01/10/2024",
      "date_iso": "2024-10-01",
      "year": 2024,
      "month": 10,
      "category": "Gender and food security and nutrition",
      "url": "https://openknowledge.fao.org/handle/20.500.14283/cd2877en",
      "summary": "",
      "article_summary": "",
      "article_text": ""
    },
    {
      "section": "publications",
      "page": 6,
      "title": "Advancing women's leadership in dryland regions through the three Rs: rights, representation and resources",
      "date": "01/10/2024",
      "date_iso": "2024-10-01",
      "year": 2024,
      "month": 10,
      "category": "Gender equality and women's empowerment",
      "url": "https://openknowledge.fao.org/handle/20.500.14283/cc9187en",
      "summary": "",
      "article_summary": "",
      "article_text": ""
    },
    {
      "section": "publications",
      "page": 6,
      "title": "Gender-responsive value chain analysis in Albania (Case studies of Elbasan, Leskovik and Puka)",
      "date": "01/10/2024",
      "date_iso": "2024-10-01",
      "year": 2024,
      "month": 10,
      "category": "Gender and inclusive food systems and value chains",
      "url": "https://openknowledge.fao.org/handle/20.500.14283/cd1282en",
      "summary": "",
      "article_summary": "",
      "article_text": ""
    },
    {
      "section": "publications",
      "page": 6,
      "title": "Training course material for climate-wise women agents",
      "date": "01/10/2024",
      "date_iso": "2024-10-01",
      "year": 2024,
      "month": 10,
      "category": "Gender and climate change, agroecology and biodiversity",
      "url": "https://openknowledge.fao.org/handle/20.500.14283/cd2842en",
      "summary": "",
      "article_summary": "",
      "article_text": ""
    },
    {
      "section": "publications",
      "page": 7,
      "title": "Step-by-step checklist for integrating a gender transformative approach throughout the project cycle",
      "date": "01/10/2024",
      "date_iso": "2024-10-01",
      "year": 2024,
      "month": 10,
      "category": "Gender analysis, gender mainstreaming and the project cycle",
      "url": "https://openknowledge.fao.org/handle/20.500.14283/cd2907en",
      "summary": "",
      "article_summary": "",
      "article_text": ""
    },
    {
      "section": "publications",
      "page": 7,
      "title": "Supporting Women’s Agrifood Cooperatives and Associations in Lebanon - GCP/LEB/030/CAN",
      "date": "01/10/2024",
      "date_iso": "2024-10-01",
      "year": 2024,
      "month": 10,
      "category": "Gender and inclusive food systems and value chains",
      "url": "https://openknowledge.fao.org/handle/20.500.14283/cd2721en",
      "summary": "",
      "article_summary": "",
      "article_text": ""
    },
    {
      "section": "publications",
      "page": 7,
      "title": "Lessons learned on establishing a \"Gender Desk\" within a national fisheries institution",
      "date": "01/10/2024",
      "date_iso": "2024-10-01",
      "year": 2024,
      "month": 10,
      "category": "Gender in fisheries and aquaculture",
      "url": "https://openknowledge.fao.org/handle/20.500.14283/cd2818en",
      "summary": "",
      "article_summary": "",
      "article_text": ""
    },
    {
      "section": "publications",
      "page": 7,
      "title": "Empowering Women, Increasing Institutional and Local Resilience and Recovering and Preserving Forestlands in West Honduras - GCP/HON/045/CAN",
      "date": "01/09/2024",
      "date_iso": "2024-09-01",
      "year": 2024,
      "month": 9,
      "category": "Gender and emergencies and resilience building",
      "url": "https://openknowledge.fao.org/handle/20.500.14283/cd2345en",
      "summary": "",
      "article_summary": "",
      "article_text": ""
    },
    {
      "section": "publications",
      "page": 7,
      "title": "Understanding the gender-related impact of the crisis in the Gaza Strip and the West Bank for an inclusive response",
      "date": "01/09/2024",
      "date_iso": "2024-09-01",
      "year": 2024,
      "month": 9,
      "category": "Gender and emergencies and resilience building",
      "url": "https://openknowledge.fao.org/handle/20.500.14283/cd2221en",
      "summary": "",
      "article_summary": "",
      "article_text": ""
    },
    {
      "section": "publications",
      "page": 7,
      "title": "Sanitary and phytosanitary measures- Making the African Continental Free Trade Area work for women (Policy brief)",
      "date": "01/08/2024",
      "date_iso": "2024-08-01",
      "year": 2024,
      "month": 8,
      "category": "Gender-responsive policy making and budgeting",
      "url": "https://openknowledge.fao.org/handle/20.500.14283/cd1028en",
      "summary": "",
      "article_summary": "",
      "article_text": ""
    },
    {
      "section": "publications",
      "page": 7,
      "title": "Facilitating gender responsive access to finance in the agrifood sector in sub-Saharan Africa",
      "date": "01/08/2024",
      "date_iso": "2024-08-01",
      "year": 2024,
      "month": 8,
      "category": "Gender and inclusive food systems and value chains",
      "url": "https://openknowledge.fao.org/handle/20.500.14283/cd2082en",
      "summary": "",
      "article_summary": "",
      "article_text": ""
    },
    {
      "section": "publications",
      "page": 7,
      "title": "Post-earthquake value chain analysis of greenhouse tomatoes, fisheries and milk products in Türkiye",
      "date": "01/08/2024",
      "date_iso": "2024-08-01",
      "year": 2024,
      "month": 8,
      "category": "Gender in fisheries and aquaculture",
      "url": "https://openknowledge.fao.org/handle/20.500.14283/cd1776en",
      "summary": "",
      "article_summary": "",
      "article_text": ""
    },
    {
      "section": "publications",
      "page": 8,
      "title": "Technical barriers to trade in the agrifood sector - Making the African Continental Free Trade Area work for women: Policy brief",
      "date": "01/08/2024",
      "date_iso": "2024-08-01",
      "year": 2024,
      "month": 8,
      "category": "Gender and inclusive food systems and value chains",
      "url": "https://openknowledge.fao.org/handle/20.500.14283/cd1030en",
      "summary": "",
      "article_summary": "",
      "article_text": ""
    },
    {
      "section": "publications",
      "page": 8,
      "title": "Report on the Third International Meeting on Gender Equity in the banana industry",
      "date": "01/08/2024",
      "date_iso": "2024-08-01",
      "year": 2024,
      "month": 8,
      "category": "Gender equality and women's empowerment",
      "url": "https://openknowledge.fao.org/handle/20.500.14283/cd1886en",
      "summary": "",
      "article_summary": "",
      "article_text": ""
    },
    {
      "section": "publications",
      "page": 8,
      "title": "Empowering Small-Scale Fisheries for Sustainable and Inclusive Food Systems - FMM/GLO/155/MUL",
      "date": "01/08/2024",
      "date_iso": "2024-08-01",
      "year": 2024,
      "month": 8,
      "category": "Gender and inclusive food systems and value chains",
      "url": "https://openknowledge.fao.org/handle/20.500.14283/cd1857en",
      "summary": "",
      "article_summary": "",
      "article_text": ""
    },
    {
      "section": "publications",
      "page": 8,
      "title": "Understanding women’s roles and trade potential along the fisheries and aquaculture value chains: Case studies from Ghana and Nigeria",
      "date": "01/08/2024",
      "date_iso": "2024-08-01",
      "year": 2024,
      "month": 8,
      "category": "Gender in fisheries and aquaculture",
      "url": "https://openknowledge.fao.org/handle/20.500.14283/cd1155en",
      "summary": "",
      "article_summary": "",
      "article_text": ""
    },
    {
      "section": "publications",
      "page": 8,
      "title": "Commit to Grow Equality - Global commitment to enhance gender equality in agrifood systems through financing and partnerships",
      "date": "01/08/2024",
      "date_iso": "2024-08-01",
      "year": 2024,
      "month": 8,
      "category": "Gender and inclusive food systems and value chains",
      "url": "https://openknowledge.fao.org/handle/20.500.14283/cd1842en",
      "summary": "",
      "article_summary": "",
      "article_text": ""
    },
    {
      "section": "publications",
      "page": 8,
      "title": "Joint Programme on Gender Transformative Approaches for Food Security and Nutrition 2023 in review",
      "date": "11/07/2024",
      "date_iso": "2024-07-11",
      "year": 2024,
      "month": 7,
      "category": "Gender and food security and nutrition",
      "url": "https://openknowledge.fao.org/handle/20.500.14283/cd1546en",
      "summary": "",
      "article_summary": "",
      "article_text": ""
    },
    {
      "section": "publications",
      "page": 8,
      "title": "Farmer Field Schools (FFS) for mutual learning and collective action",
      "date": "01/07/2024",
      "date_iso": "2024-07-01",
      "year": 2024,
      "month": 7,
      "category": "Gender and rural advisory services",
      "url": "https://openknowledge.fao.org/handle/20.500.14283/cd1624en",
      "summary": "",
      "article_summary": "",
      "article_text": ""
    },
    {
      "section": "publications",
      "page": 8,
      "title": "Diagnostic of gender and age norms in financial inclusion: A pilot study in five districts of Malawi",
      "date": "01/07/2024",
      "date_iso": "2024-07-01",
      "year": 2024,
      "month": 7,
      "category": "Gender and rural financial services",
      "url": "https://openknowledge.fao.org/handle/20.500.14283/cd1373en",
      "summary": "",
      "article_summary": "",
      "article_text": ""
    },
    {
      "section": "publications",
      "page": 9,
      "title": "Women’s financial inclusion: Alternative collateral approaches for closing the credit gap for women in agrifood systems",
      "date": "01/07/2024",
      "date_iso": "2024-07-01",
      "year": 2024,
      "month": 7,
      "category": "Gender and rural financial services",
      "url": "https://openknowledge.fao.org/handle/20.500.14283/cd1487en",
      "summary": "",
      "article_summary": "",
      "article_text": ""
    },
    {
      "section": "publications",
      "page": 9,
      "title": "The State of the World’s Forests 2024",
      "date": "01/07/2024",
      "date_iso": "2024-07-01",
      "year": 2024,
      "month": 7,
      "category": "Gender in forestry and agroforestry",
      "url": "https://openknowledge.fao.org/handle/20.500.14283/cd1211en",
      "summary": "",
      "article_summary": "",
      "article_text": ""
    },
    {
      "section": "publications",
      "page": 9,
      "title": "Empowering African Women And Boosting their Livelihoods through Agricultural Trade - FMM/GLO/169/MUL",
      "date": "01/07/2024",
      "date_iso": "2024-07-01",
      "year": 2024,
      "month": 7,
      "category": "Gender equality and women's empowerment",
      "url": "https://openknowledge.fao.org/handle/20.500.14283/cd1684en",
      "summary": "",
      "article_summary": "",
      "article_text": ""
    },
    {
      "section": "publications",
      "page": 9,
      "title": "Empowering Rural Women: Combating Gender Inequality in Agriculture - FMM/GLO/138/MUL",
      "date": "01/07/2024",
      "date_iso": "2024-07-01",
      "year": 2024,
      "month": 7,
      "category": "Gender equality and women's empowerment",
      "url": "https://openknowledge.fao.org/handle/20.500.14283/cd1630en",
      "summary": "",
      "article_summary": "",
      "article_text": ""
    },
    {
      "section": "publications",
      "page": 9,
      "title": "Post-harvest management: bridging gaps and embracing innovations",
      "date": "01/07/2024",
      "date_iso": "2024-07-01",
      "year": 2024,
      "month": 7,
      "category": "Gender and innovative and labour-saving technologies",
      "url": "https://openknowledge.fao.org/handle/20.500.14283/cd1185en",
      "summary": "",
      "article_summary": "",
      "article_text": ""
    },
    {
      "section": "publications",
      "page": 9,
      "title": "Empowering women in fisheries value chains - Good practices and lessons learned from the Coastal Fisheries Initiative",
      "date": "01/07/2024",
      "date_iso": "2024-07-01",
      "year": 2024,
      "month": 7,
      "category": "Gender in fisheries and aquaculture",
      "url": "https://openknowledge.fao.org/handle/20.500.14283/cd0879en",
      "summary": "",
      "article_summary": "",
      "article_text": ""
    },
    {
      "section": "publications",
      "page": 9,
      "title": "Intersectionality: A pathway for more inclusive, youth-oriented and gender-responsive agrifood systems",
      "date": "01/07/2024",
      "date_iso": "2024-07-01",
      "year": 2024,
      "month": 7,
      "category": "Gender and inclusive food systems and value chains",
      "url": "https://openknowledge.fao.org/handle/20.500.14283/cd1375en",
      "summary": "",
      "article_summary": "",
      "article_text": ""
    },
    {
      "section": "publications",
      "page": 9,
      "title": "Commitments matrix - Global commitment to enhance gender equality in agrifood systems through financing and partnerships",
      "date": "13/06/2024",
      "date_iso": "2024-06-13",
      "year": 2024,
      "month": 6,
      "category": "Gender and inclusive food systems and value chains",
      "url": "https://openknowledge.fao.org/handle/20.500.14283/cc9848en",
      "summary": "",
      "article_summary": "",
      "article_text": ""
    },
    {
      "section": "publications",
      "page": 10,
      "title": "Support to Use Sex Disaggregated Data in Agriculture to Make Second Generation National Agriculture Investment Plans (NAIPS) and Regional Agriculture Investment Plans (RAIPS) Gender Responsive - TCP/RAF/3803",
      "date": "01/06/2024",
      "date_iso": "2024-06-01",
      "year": 2024,
      "month": 6,
      "category": "Gender statistics and sex-disaggregated data",
      "url": "https://openknowledge.fao.org/handle/20.500.14283/cd1297en",
      "summary": "",
      "article_summary": "",
      "article_text": ""
    },
    {
      "section": "publications",
      "page": 10,
      "title": "The State of World Fisheries and Aquaculture 2024",
      "date": "01/06/2024",
      "date_iso": "2024-06-01",
      "year": 2024,
      "month": 6,
      "category": "Gender in fisheries and aquaculture",
      "url": "https://openknowledge.fao.org/handle/20.500.14283/cd0683en",
      "summary": "",
      "article_summary": "",
      "article_text": ""
    },
    {
      "section": "publications",
      "page": 10,
      "title": "Understanding women’s roles and trade potential along the soybean-to-poultry regional value chain: Case studies from Malawi and South Africa",
      "date": "01/06/2024",
      "date_iso": "2024-06-01",
      "year": 2024,
      "month": 6,
      "category": "Gender and inclusive food systems and value chains",
      "url": "https://openknowledge.fao.org/handle/20.500.14283/cc8570en",
      "summary": "",
      "article_summary": "",
      "article_text": ""
    },
    {
      "section": "publications",
      "page": 10,
      "title": "Kosovo gender profile for agriculture and rural livelihoods",
      "date": "01/06/2024",
      "date_iso": "2024-06-01",
      "year": 2024,
      "month": 6,
      "category": "Gender equality and women's empowerment",
      "url": "https://openknowledge.fao.org/handle/20.500.14283/cd1154en",
      "summary": "",
      "article_summary": "",
      "article_text": ""
    },
    {
      "section": "publications",
      "page": 10,
      "title": "Land tenure in Asia and the Pacific - Women’s empowerment and gender equality",
      "date": "01/06/2024",
      "date_iso": "2024-06-01",
      "year": 2024,
      "month": 6,
      "category": "Gender and land and water",
      "url": "https://openknowledge.fao.org/handle/20.500.14283/cd1076en",
      "summary": "",
      "article_summary": "",
      "article_text": ""
    },
    {
      "section": "publications",
      "page": 10,
      "title": "A toolkit for incorporating fish into the home-grown school feeding programme",
      "date": "01/06/2024",
      "date_iso": "2024-06-01",
      "year": 2024,
      "month": 6,
      "category": "Gender equality and women's empowerment",
      "url": "https://openknowledge.fao.org/handle/20.500.14283/cd0278en",
      "summary": "",
      "article_summary": "",
      "article_text": ""
    },
    {
      "section": "publications",
      "page": 10,
      "title": "Regional Gender Equality Strategy and Action Plan 2024–2027 for the Near East and North Africa region",
      "date": "01/06/2024",
      "date_iso": "2024-06-01",
      "year": 2024,
      "month": 6,
      "category": "Gender equality and women's empowerment",
      "url": "https://openknowledge.fao.org/handle/20.500.14283/cd0923en",
      "summary": "",
      "article_summary": "",
      "article_text": ""
    },
    {
      "section": "publications",
      "page": 10,
      "title": "Towards gender-responsive agricultural extension services in Albania",
      "date": "01/06/2024",
      "date_iso": "2024-06-01",
      "year": 2024,
      "month": 6,
      "category": "Gender and rural advisory services",
      "url": "https://openknowledge.fao.org/handle/20.500.14283/cc7701en",
      "summary": "",
      "article_summary": "",
      "article_text": ""
    }
  ]
}